qubitscope/__init__.py
qubitscope-0.0.1.dist-info/licenses/LICENSE
qubitscope-0.0.1.dist-info/METADATA
qubitscope-0.0.1.dist-info/WHEEL
qubitscope-0.0.1.dist-info/top_level.txt
qubitscope-0.0.1.dist-info/RECORD
