Metadata-Version: 2.4
Name: qubitscope
Version: 0.0.1
Summary: qubit analysis tool
Author-email: Yaqiang Sun <sunyaking@163.com>
License: GPL-3.0
Requires-Python: >=3.12
License-File: LICENSE
Dynamic: license-file
